stark/__init__.py
stark/core/__init__.py
stark/core/command.py
stark/core/commands_context.py
stark/core/commands_context_processor.py
stark/core/commands_manager.py
stark/core/health_check.py
stark/core/parsing.py
stark/core/patterns/__init__.py
stark/core/patterns/pattern.py
stark/core/patterns/rules.py
stark/core/processors/__init__.py
stark/core/processors/search_processor.py
stark/core/processors/spacy_ner_processor.py
stark/core/types/__init__.py
stark/core/types/location.py
stark/core/types/object.py
stark/core/types/slots.py
stark/core/types/string.py
stark/core/types/word.py
stark/general/blockage_detector.py
stark/general/cache.py
stark/general/classproperty.py
stark/general/dependencies.py
stark/general/json_encoder.py
stark/interfaces/gcloud.py
stark/interfaces/protocols.py
stark/interfaces/silero.py
stark/interfaces/vosk.py
stark/tools/common/span.py
stark/tools/dictionary/!examples.py
stark/tools/dictionary/__init__.py
stark/tools/dictionary/dictionary.py
stark/tools/dictionary/models.py
stark/tools/dictionary/nl_dictionary_name.py
stark/tools/dictionary/storage/__init__.py
stark/tools/dictionary/storage/storage_memory.py
stark/tools/dictionary/storage/storage_sqlite.py
stark/tools/levenshtein/__init__.py
stark/tools/levenshtein/levenshtein.pyi
stark/tools/levenshtein/levenshtein.pyx
stark/tools/phonetic/simplephone.py
stark/tools/phonetic/transcription/__init__.py
stark/tools/phonetic/transcription/epitran.py
stark/tools/phonetic/transcription/espeak.py
stark/tools/phonetic/transcription/ipa2lat.py
stark/tools/phonetic/transcription/protocol.py
stark/tools/sliding_window_parser.py
stark/tools/strtools.py
stark/voice_assistant/__init__.py
stark/voice_assistant/mode.py
stark/voice_assistant/voice_assistant.py
stark_engine-4.3.0.dist-info/METADATA
stark_engine-4.3.0.dist-info/WHEEL
stark_engine-4.3.0.dist-info/licenses/LICENSE.md
stark_engine-4.3.0.dist-info/RECORD
