Metadata-Version: 2.4
Name: stark-engine
Version: 4.3.0
Summary: S.T.A.R.K - Speech and Text Algorithmic Recognition Kit. Modern framework for creating powerfull voice assistants.
License: CC BY-NC-SA 4.0
License-File: LICENSE.md
Keywords: python,open-source,natural-language-processing,framework,cross-platform,natural-language,voice,voice-commands,python3,voice-recognition,speech-recognition,speech-to-text,community-project,voice-assistant,voice-interface,NLP,machine-learning,AI,text-analysis,stark,stark-place,stark-engine,mark parker
Author: MarkParker5
Author-email: mark@parker-programs.com
Requires-Python: >=3.12,<3.15
Classifier: License :: Other/Proprietary License
Classifier: Programming Language :: Python :: 3
Classifier: Programming Language :: Python :: 3.12
Classifier: Programming Language :: Python :: 3.13
Classifier: Programming Language :: Python :: 3.14
Provides-Extra: all
Provides-Extra: gcloud
Provides-Extra: silero
Provides-Extra: sound
Provides-Extra: spacy
Provides-Extra: vosk
Requires-Dist: asyncer (>=0.0.2,<0.0.3)
Requires-Dist: google-cloud-texttospeech (>=2.14.1,<3.0.0) ; extra == "gcloud" or extra == "all"
Requires-Dist: numpy (>=2.3.3,<3.0.0) ; extra == "silero" or extra == "all"
Requires-Dist: pydantic (>=2.0.0,<3.0.0)
Requires-Dist: sounddevice (>=0.4.5,<0.5.0) ; extra == "gcloud" or extra == "vosk" or extra == "silero" or extra == "sound" or extra == "all"
Requires-Dist: soundfile (>=0.11.0,<0.12.0) ; extra == "gcloud" or extra == "sound" or extra == "all"
Requires-Dist: spacy (>=3.8.11,<4.0.0) ; extra == "spacy" or extra == "all"
Requires-Dist: torch (>=1.13.1,<2.0.0) ; extra == "silero" or extra == "all"
Requires-Dist: vosk (==0.3.44) ; extra == "vosk" or extra == "all"
Project-URL: Documentation, https://stark.markparker.me
Project-URL: Homepage, https://pypi.org/project/stark-engine/
Project-URL: Repository, https://github.com/MarkParker5/STARK
